montpy/__init__.py
montpy/mc.py
montpy/qmc.py
montpy-0.1.2.dist-info/LICENSE
montpy-0.1.2.dist-info/METADATA
montpy-0.1.2.dist-info/WHEEL
montpy-0.1.2.dist-info/RECORD
