Metadata-Version: 2.1
Name: montpy
Version: 0.1.2
Summary: Library implementing Monte Carlo and Quasi-Monte Carlo methods for integral evaluation
Author: Pietro Zanotta
Author-email: zanottapietro1@gmail.com
Requires-Python: >3.8
Classifier: Programming Language :: Python :: 3
Classifier: Programming Language :: Python :: 3.9
Classifier: Programming Language :: Python :: 3.10
Classifier: Programming Language :: Python :: 3.11
Classifier: Programming Language :: Python :: 3.12
Requires-Dist: numpy (>=1.26.4,<2.0.0)
Requires-Dist: scipy (>=1.11.4,<2.0.0)
